{
  "project_info": {
    "project_number": "322150511311",
    "project_id": "socially-cb039",
    "storage_bucket": "socially-cb039.firebasestorage.app"
  },
  "client": [
    {
      "client_info": {
        "mobilesdk_app_id": "1:322150511311:android:fe9031dcb687d4cc2d3dba",
        "android_client_info": {
          "package_name": "com.example.socially"
        }
      },
      "oauth_client": [
        {
          "client_id": "322150511311-a1jc7vqptom1dvdoloupsufuumnrlb1n.apps.googleusercontent.com",
          "client_type": 1,
          "android_info": {
            "package_name": "com.example.socially",
            "certificate_hash": "976217fc0f7364e2b8f2780974e20e9312c5364b"
          }
        },
        {
          "client_id": "322150511311-josces1ov45gqrgg9q2b83d7nqfvd3eo.apps.googleusercontent.com",
          "client_type": 3
        }
      ],
      "api_key": [
        {
          "current_key": "AIzaSyAmzl5EGSQ_3MpALSxE2vPfACyg1sNXhH4"
        }
      ],
      "services": {
        "appinvite_service": {
          "other_platform_oauth_client": [
            {
              "client_id": "322150511311-josces1ov45gqrgg9q2b83d7nqfvd3eo.apps.googleusercontent.com",
              "client_type": 3
            },
            {
              "client_id": "322150511311-7t8lb90ltngbfo3na2sbc33mfik89dov.apps.googleusercontent.com",
              "client_type": 2,
              "ios_info": {
                "bundle_id": "com.example.socially"
              }
            }
          ]
        }
      }
    }
  ],
  "configuration_version": "1"
}